MANIFEST.in
README.md
setup.py
jpdataset/__init__.py
jpdataset/nanodcal/bulk_iron/LDA_SP/bcc_primitive_1x1x1/CalculatedResults.mat
jpdataset/nanodcal/bulk_iron/LDA_SP/bcc_primitive_1x1x1/NanodcalStructObject.mat
jpdataset/nanodcal/bulk_iron/LDA_SP/bcc_primitive_1x1x1/TotalEnergy.mat
jpdataset/nanodcal/bulk_iron/LDA_SP/bcc_primitive_1x1x1/atoms.xyz
jpdataset/nanodcal/bulk_iron/LDA_SP/bcc_primitive_1x1x1/bcc_primitive_1x1x1.e30411
jpdataset/nanodcal/bulk_iron/LDA_SP/bcc_primitive_1x1x1/bcc_primitive_1x1x1.o30411
jpdataset/nanodcal/bulk_iron/LDA_SP/bcc_primitive_1x1x1/log.txt
jpdataset/nanodcal/bulk_iron/LDA_SP/bcc_primitive_1x1x1/nanodcal.pbs
jpdataset/nanodcal/bulk_iron/LDA_SP/bcc_primitive_1x1x1/scf.input
jpdataset/nanodcal/bulk_iron/LDA_SP/bcc_primitive_1x1x1/scf.output
jpdataset/nanodcal/bulk_iron/LDA_SP/bcc_primitive_1x1x1/analysis/nad_bandStructure/BandStructure.mat
jpdataset/nanodcal/bulk_iron/LDA_SP/bcc_primitive_1x1x1/analysis/nad_bandStructure/CalculatedResults.mat
jpdataset/nanodcal/bulk_iron/LDA_SP/bcc_primitive_1x1x1/analysis/nad_bandStructure/bandEnergies_dn.dat
jpdataset/nanodcal/bulk_iron/LDA_SP/bcc_primitive_1x1x1/analysis/nad_bandStructure/bandEnergies_up.dat
jpdataset/nanodcal/bulk_iron/LDA_SP/bcc_primitive_1x1x1/analysis/nad_bandStructure/log.txt
jpdataset/nanodcal/bulk_iron/LDA_SP/bcc_primitive_1x1x1/analysis/nad_bandStructure/main.input
jpdataset/nanodcal/bulk_iron/LDA_SP/bcc_primitive_1x1x1/analysis/nad_bandStructure/main.output
jpdataset/nanodcal/bulk_iron/LDA_SP/bcc_primitive_1x1x1/analysis/nad_bandStructure/nanodcal.pbs
jpdataset/nanodcal/bulk_iron/LDA_SP/bcc_primitive_1x1x1/analysis/nad_bandStructure/parse.m
jpdataset/nanodcal/bulk_iron/LDA_SP/bcc_primitive_1x1x1/analysis/nad_bandStructure/run_bandStructure.e30413
jpdataset/nanodcal/bulk_iron/LDA_SP/bcc_primitive_1x1x1/analysis/nad_bandStructure/run_bandStructure.o30413
jpdataset/nanodcal/bulk_iron/LDA_SP/bcc_primitive_1x1x1/analysis/nad_bandStructure_v2/BandStructure.mat
