Metadata-Version: 2.2
Name: junpy-dataset
Version: 0.2.0
Summary: JunPy-dataset is a collection of data used in JunPy tests and examples.
Home-page: https://labstt.phy.ncu.edu.tw/junpy
Author: Bao-Huei Huang
Author-email: lise811020@gmail.com
License: GPL
Platform: Unix
Platform: macOS
Platform: Windows
Classifier: Programming Language :: Python :: 3 :: Only
Classifier: Programming Language :: Python :: 3.6
Classifier: Programming Language :: Python :: 3.7
Classifier: Programming Language :: Python :: 3.8
Classifier: Programming Language :: Python :: 3.9
Requires-Python: >=3.6.0
Dynamic: author
Dynamic: author-email
Dynamic: classifier
Dynamic: home-page
Dynamic: license
Dynamic: platform
Dynamic: requires-python
Dynamic: summary
